claudette/__init__.py
claudette/__main__.py
claudette/assistant.py
claudette/audio_processing.py
claudette/hotkey.py
claudette/notifications.py
claudette/offline.py
claudette/personalities.py
claudette/skills.py
claudette/sounds.py
claudette/tray.py
claudette/web/__init__.py
claudette/web/server.py
claudette/web/state.py
claudette/web/routes/__init__.py
claudette/web/routes/api.py
claudette/web/routes/websocket.py
claudette/web/static/index.html
claudette/web/static/css/styles.css
claudette/web/static/js/app.js
claudette_voice-0.1.4.dist-info/METADATA
claudette_voice-0.1.4.dist-info/WHEEL
claudette_voice-0.1.4.dist-info/entry_points.txt
claudette_voice-0.1.4.dist-info/licenses/LICENSE
claudette_voice-0.1.4.dist-info/RECORD
