Metadata-Version: 2.4
Name: claudette-voice
Version: 0.1.4
Summary: A sophisticated AI voice assistant with 1940s British charm - voice interface for Claude CLI
Project-URL: Homepage, https://github.com/cyberkoder/claudette
Project-URL: Documentation, https://github.com/cyberkoder/claudette#readme
Project-URL: Repository, https://github.com/cyberkoder/claudette
Project-URL: Issues, https://github.com/cyberkoder/claudette/issues
Author: Claudette Contributors
License-Expression: MIT
License-File: LICENSE
Keywords: ai,claude,speech-recognition,tts,voice-assistant,whisper
Classifier: Development Status :: 3 - Alpha
Classifier: Environment :: Console
Classifier: Intended Audience :: Developers
Classifier: Intended Audience :: End Users/Desktop
Classifier: License :: OSI Approved :: MIT License
Classifier: Operating System :: MacOS
Classifier: Operating System :: POSIX :: Linux
Classifier: Programming Language :: Python :: 3
Classifier: Programming Language :: Python :: 3.10
Classifier: Programming Language :: Python :: 3.11
Classifier: Programming Language :: Python :: 3.12
Classifier: Topic :: Multimedia :: Sound/Audio :: Speech
Classifier: Topic :: Scientific/Engineering :: Artificial Intelligence
Requires-Python: >=3.10
Requires-Dist: edge-tts>=6.1.0
Requires-Dist: numpy>=1.24.0
Requires-Dist: packaging>=21.0
Requires-Dist: pygame>=2.5.0
Requires-Dist: pyyaml>=6.0
Requires-Dist: requests>=2.28.0
Requires-Dist: sounddevice>=0.4.6
Requires-Dist: torch>=2.0.0
Requires-Dist: torchaudio>=2.0.0
Provides-Extra: all
Requires-Dist: black>=23.0.0; extra == 'all'
Requires-Dist: build>=1.0.0; extra == 'all'
Requires-Dist: fastapi>=0.109.0; extra == 'all'
Requires-Dist: faster-whisper>=1.0.0; extra == 'all'
Requires-Dist: mypy>=1.0.0; extra == 'all'
Requires-Dist: noisereduce>=2.0.0; extra == 'all'
Requires-Dist: pillow>=9.0.0; extra == 'all'
Requires-Dist: plyer>=2.1.0; extra == 'all'
Requires-Dist: psutil>=5.9.0; extra == 'all'
Requires-Dist: pynput>=1.7.6; extra == 'all'
Requires-Dist: pystray>=0.19.0; extra == 'all'
Requires-Dist: pytest-asyncio>=0.21.0; extra == 'all'
Requires-Dist: pytest>=7.0.0; extra == 'all'
Requires-Dist: ruff>=0.1.0; extra == 'all'
Requires-Dist: scipy>=1.10.0; extra == 'all'
Requires-Dist: twine>=4.0.0; extra == 'all'
Requires-Dist: uvicorn[standard]>=0.27.0; extra == 'all'
Provides-Extra: audio
Requires-Dist: noisereduce>=2.0.0; extra == 'audio'
Requires-Dist: scipy>=1.10.0; extra == 'audio'
Provides-Extra: dev
Requires-Dist: black>=23.0.0; extra == 'dev'
Requires-Dist: build>=1.0.0; extra == 'dev'
Requires-Dist: mypy>=1.0.0; extra == 'dev'
Requires-Dist: pytest-asyncio>=0.21.0; extra == 'dev'
Requires-Dist: pytest>=7.0.0; extra == 'dev'
Requires-Dist: ruff>=0.1.0; extra == 'dev'
Requires-Dist: twine>=4.0.0; extra == 'dev'
Provides-Extra: hotkey
Requires-Dist: pynput>=1.7.6; extra == 'hotkey'
Provides-Extra: local
Requires-Dist: faster-whisper>=1.0.0; extra == 'local'
Provides-Extra: notifications
Requires-Dist: plyer>=2.1.0; extra == 'notifications'
Provides-Extra: system
Requires-Dist: psutil>=5.9.0; extra == 'system'
Provides-Extra: tray
Requires-Dist: pillow>=9.0.0; extra == 'tray'
Requires-Dist: pystray>=0.19.0; extra == 'tray'
Provides-Extra: web
Requires-Dist: fastapi>=0.109.0; extra == 'web'
Requires-Dist: uvicorn[standard]>=0.27.0; extra == 'web'
